ovos_PHAL_plugin_dashboard/__init__.py
ovos_PHAL_plugin_dashboard-0.0.1.dist-info/LICENSE
ovos_PHAL_plugin_dashboard-0.0.1.dist-info/METADATA
ovos_PHAL_plugin_dashboard-0.0.1.dist-info/WHEEL
ovos_PHAL_plugin_dashboard-0.0.1.dist-info/entry_points.txt
ovos_PHAL_plugin_dashboard-0.0.1.dist-info/top_level.txt
ovos_PHAL_plugin_dashboard-0.0.1.dist-info/zip-safe
ovos_PHAL_plugin_dashboard-0.0.1.dist-info/RECORD
